neurogenesis_napari/__init__.py
neurogenesis_napari/napari.yaml
neurogenesis_napari/settings.py
neurogenesis_napari/typing.py
neurogenesis_napari/classification/representation_based/vae.py
neurogenesis_napari/preprocessing/cellpose_denoising.py
neurogenesis_napari/preprocessing/colour_normalization.py
neurogenesis_napari/preprocessing/good_img.png
neurogenesis_napari/segmentation/cs.py
neurogenesis_napari/segmentation/dapi_cellpose.py
neurogenesis_napari/widget_utils/__init__.py
neurogenesis_napari/widget_utils/classification.py
neurogenesis_napari/widget_utils/edit_prediction.py
neurogenesis_napari/widget_utils/geometry.py
neurogenesis_napari/widget_utils/image.py
neurogenesis_napari/widget_utils/inspect.py
neurogenesis_napari/widget_utils/logging_to_napari.py
neurogenesis_napari/widget_utils/model_hub.py
neurogenesis_napari/widget_utils/progress.py
neurogenesis_napari/widget_utils/save_csv.py
neurogenesis_napari/widget_utils/segmentation.py
neurogenesis_napari/widgets/__init__.py
neurogenesis_napari/widgets/normalize_and_denoise.py
neurogenesis_napari/widgets/segment.py
neurogenesis_napari/widgets/segment_and_classify.py
neurogenesis_napari-0.1.0a2.dist-info/METADATA
neurogenesis_napari-0.1.0a2.dist-info/WHEEL
neurogenesis_napari-0.1.0a2.dist-info/entry_points.txt
neurogenesis_napari-0.1.0a2.dist-info/licenses/LICENSE
neurogenesis_napari-0.1.0a2.dist-info/RECORD
