Metadata-Version: 2.4
Name: neurogenesis-napari
Version: 0.1.0a2
Summary: A napari plugin to segment and classify cells.
Project-URL: Repository, https://github.com/tum-ai/neurogenesis_napari
Author-email: "TUM.ai" <contact@tum-ai.com>
License: 
License-File: LICENSE
Classifier: Development Status :: 2 - Pre-Alpha
Classifier: Framework :: napari
Classifier: Intended Audience :: Developers
Classifier: License :: OSI Approved :: MIT License
Classifier: Operating System :: MacOS :: MacOS X
Classifier: Operating System :: Microsoft :: Windows
Classifier: Operating System :: OS Independent
Classifier: Operating System :: POSIX :: Linux
Classifier: Programming Language :: Python :: 3.10
Classifier: Programming Language :: Python :: 3.11
Classifier: Programming Language :: Python :: 3.12
Classifier: Topic :: Scientific/Engineering :: Image Processing
Requires-Python: >=3.10
Requires-Dist: cellpose==3.1.1.2
Requires-Dist: huggingface-hub>=0.33.0
Requires-Dist: magicgui
Requires-Dist: napari-czifile2
Requires-Dist: napari[pyqt5]
Requires-Dist: numpy==1.26.4
Requires-Dist: opencv-python==4.11.0.86
Requires-Dist: pandas==2.3.0
Requires-Dist: qtpy
Requires-Dist: sam2==1.1.0
Requires-Dist: scikit-image==0.25.2
Requires-Dist: scikit-learn==1.2.2
Requires-Dist: tifffile<=2023.4.12
Requires-Dist: torch==2.7.1
